xepmts/__init__.py
xepmts/cli.py
xepmts/db/__init__.py
xepmts/db/client.py
xepmts/db/endpoints.py
xepmts/settings.py
xepmts/streams/__init__.py
xepmts/streams/daq.py
xepmts/streams/sc.py
xepmts-0.5.9.dist-info/entry_points.txt
xepmts-0.5.9.dist-info/LICENSE
xepmts-0.5.9.dist-info/WHEEL
xepmts-0.5.9.dist-info/METADATA
xepmts-0.5.9.dist-info/RECORD
