Metadata-Version: 2.1
Name: xepmts
Version: 0.5.9
Summary: Python client for accessing the XENON experiment PMT data.
Home-page: https://github.com/jmosbacher/xepmts
License: MIT
Author: Yossi Mosbacher
Author-email: joe.mosbacher@gmail.com
Requires-Python: >=3.8,<3.11
Classifier: Development Status :: 2 - Pre-Alpha
Classifier: Intended Audience :: Developers
Classifier: License :: OSI Approved :: MIT License
Classifier: Natural Language :: English
Classifier: Programming Language :: Python :: 3
Classifier: Programming Language :: Python :: 3.10
Classifier: Programming Language :: Python :: 3.6
Classifier: Programming Language :: Python :: 3.7
Classifier: Programming Language :: Python :: 3.8
Classifier: Programming Language :: Python :: 3.9
Provides-Extra: dask
Provides-Extra: full
Provides-Extra: live
Provides-Extra: plotting
Requires-Dist: click
Requires-Dist: dask[dataframe] (>=2021.2.0,<2022.0.0); extra == "full"
Requires-Dist: eve-panel (>=0.3.27,<0.4.0)
Requires-Dist: hvplot (>=0.7.0,<0.8.0); extra == "plotting" or extra == "full"
Requires-Dist: streamz; extra == "live" or extra == "full"
Requires-Dist: toml (>=0.10.2,<0.11.0)
Requires-Dist: xeauth (>=0.1.19,<0.2.0)
Requires-Dist: xepmts-endpoints (>=0.1.4,<0.2.0)
Project-URL: Documentation, https://xepmts.readthedocs.io/
